flask_alchy.py
Flask_Alchy-0.5.0.dist-info/METADATA
Flask_Alchy-0.5.0.dist-info/DESCRIPTION.rst
Flask_Alchy-0.5.0.dist-info/metadata.json
Flask_Alchy-0.5.0.dist-info/top_level.txt
Flask_Alchy-0.5.0.dist-info/WHEEL
Flask_Alchy-0.5.0.dist-info/RECORD
