Metadata-Version: 2.0
Name: Flask-Alchy
Version: 0.5.0
Summary: Flask extension for alchy
Home-page: https://github.com/dgilland/flask-alchy
Author: Derrick Gilland
Author-email: dgilland@gmail.com
License: MIT
Keywords: flask alchy sqlalchemy databases
Platform: UNKNOWN
Classifier: Development Status :: 4 - Beta
Classifier: Environment :: Web Environment
Classifier: Intended Audience :: Developers
Classifier: Framework :: Flask
Classifier: Operating System :: OS Independent
Classifier: Programming Language :: Python
Classifier: License :: OSI Approved :: MIT License
Classifier: Topic :: Internet :: WWW/HTTP :: Dynamic Content
Requires-Dist: alchy (>=2.2.0)
Requires-Dist: Flask-SQLAlchemy (>=2.1.0)
